hat/chatter/__init__.py
hat/chatter/sbs_repo.json
hat_chatter-0.5.11.dist-info/LICENSE
hat_chatter-0.5.11.dist-info/METADATA
hat_chatter-0.5.11.dist-info/WHEEL
hat_chatter-0.5.11.dist-info/top_level.txt
hat_chatter-0.5.11.dist-info/zip-safe
hat_chatter-0.5.11.dist-info/RECORD
