Metadata-Version: 2.1
Name: hat-chatter
Version: 0.5.11
Summary: Hat Chatter protocol
Home-page: https://github.com/hat-open/hat-chatter
License: Apache-2.0
Classifier: Programming Language :: Python :: 3
Classifier: License :: OSI Approved :: Apache Software License
Requires-Python: >=3.10
License-File: LICENSE
Requires-Dist: hat-aio (~=0.7.8)
Requires-Dist: hat-json (~=0.5.19)
Requires-Dist: hat-sbs (~=0.6.4)
